[{"id":"accidentallyinlove","name":"Accidentally in Love","artist":"Counting Crows","fake":false,"master":true,"context":929,"song_id":751,"songname":"accidentallyinlove","tracks_count":[4,1,2,2,2,0],"pans":[0,0,-1,1,0,-1,1,-1,1,-1,1],"vols":[-0.5,-1,-4,-4,-2,-3,-3,-1.5,-1.5,-3.5,-3.5],"cores":[-1,-1,-1,-1,-1,1,1,-1,-1,-1,-1],"vocal_parts":1,"song_scroll_speed":2300,"bank":"sfx/tambourine_bank.milo","anim_tempo":32,"preview":[33030,63030],"rank_drum":155,"rank_guitar":212,"rank_bass":161,"rank_vocals":193,"rank_band":182,"genre":"rock","vocal_gender":"male","format":10,"version":30,"album_art":true,"album_name":"Shrek 2: Motion Picture Soundtrack","album_track_number":1,"year_released":2004,"rating":1,"game_origin":"lego","base_points":473980,"encoding":"latin1","drum_bank":"sfx/rb2_kit01_bank.milo","vocal_tonic_note":7,"song_tonality":0,"extra_authoring":["disc_update"],"rank_keys":290,"rank_real_keys":300,"keys_author":"SonicSBL","song_length":195000,"solo":["guitar"]},{"id":"aliensexist","name":"Aliens Exist","artist":"blink-182","fake":false,"master":true,"context":909,"song_id":752,"songname":"aliensexist","tracks_count":[5,1,2,2,0,2],"pans":[0,-1,1,-1,1,0,-1,1,-1,1,-1,1],"vols":[-0.5,-1,-1,-4,-4,-4,-3,-3,-3.5,-3.5,-5,-5],"cores":[-1,-1,-1,-1,-1,-1,1,1,-1,-1,-1,-1],"vocal_parts":2,"song_scroll_speed":2300,"bank":"sfx/handclap_bank.milo","anim_tempo":32,"preview":[33093,61138],"rank_drum":387,"rank_guitar":212,"rank_bass":225,"rank_vocals":145,"rank_band":287,"genre":"punk","vocal_gender":"male","format":10,"version":3,"album_art":true,"album_name":"Enema of the State","album_track_number":3,"year_released":1999,"rating":1,"game_origin":"lego","base_points":567353,"encoding":"latin1","drum_bank":"sfx/rb2_kit01_bank.milo","vocal_tonic_note":11,"song_tonality":0,"extra_authoring":["disc_update"],"song_length":197727,"solo":["vocal_percussion"],"alternate_path":true},{"id":"apunk","name":"A-Punk","artist":"Vampire Weekend","fake":false,"master":true,"context":949,"song_id":753,"songname":"apunk","tracks_count":[4,1,2,2,0,2],"pans":[0,0,-1,1,0,-1,1,-1,1,-1,1],"vols":[-0.5,-0.5,-2,-2,-1,-3,-3,-2.5,-2.5,-1.5,-1.5],"cores":[-1,-1,-1,-1,-1,1,1,-1,-1,-1,-1],"vocal_parts":1,"song_scroll_speed":2300,"bank":"sfx/handclap_bank.milo","anim_tempo":64,"preview":[33071,61331],"rank_drum":271,"rank_guitar":221,"rank_bass":231,"rank_vocals":174,"rank_band":257,"genre":"indierock","vocal_gender":"male","format":10,"version":3,"album_art":true,"album_name":"Vampire Weekend","album_track_number":3,"year_released":2008,"rating":1,"game_origin":"lego","base_points":404304,"encoding":"latin1","drum_bank":"sfx/rb2_kit01_bank.milo","vocal_tonic_note":2,"song_tonality":0,"extra_authoring":["disc_update"],"upgrade_version":1,"rank_real_guitar":407,"rank_real_bass":362,"real_guitar_tuning":[0,0,0,0,0,0],"real_bass_tuning":[0,0,0,0],"strings_author":"RK","song_length":141363,"solo":["vocal_percussion"]},{"id":"breakout","name":"Breakout","artist":"Foo Fighters","fake":false,"master":true,"context":945,"song_id":754,"songname":"breakout","tracks_count":[4,1,2,2,0,2],"pans":[0,0,-1,1,0,-1,1,-1,1,-1,1],"vols":[-1,-1,-3,-3,-2.5,-3,-3,-1,-1,-4,-4],"cores":[-1,-1,-1,-1,-1,1,1,-1,-1,-1,-1],"vocal_parts":2,"song_scroll_speed":2300,"bank":"sfx/handclap_bank.milo","anim_tempo":64,"preview":[25027,53294],"rank_drum":309,"rank_guitar":192,"rank_bass":178,"rank_vocals":194,"rank_band":256,"genre":"alternative","vocal_gender":"male","format":10,"version":3,"album_art":true,"album_name":"There Is Nothing Left to Lose","album_track_number":2,"year_released":1999,"rating":1,"game_origin":"lego","base_points":580156,"encoding":"latin1","drum_bank":"sfx/rb2_kit01_bank.milo","vocal_tonic_note":11,"song_tonality":0,"extra_authoring":["disc_update"],"song_length":207272,"solo":["guitar"]},{"id":"checkyesjuliet","name":"Check Yes Juliet","artist":"We the Kings","fake":false,"master":true,"context":946,"song_id":755,"songname":"checkyesjuliet","tracks_count":[5,1,2,2,2,0],"pans":[0,-1,1,-1,1,0,-1,1,-1,1,-1,1],"vols":[-0.5,-1,-1,-4,-4,-5,-3.5,-3.5,-2,-2,-2.5,-2.5],"cores":[-1,-1,-1,-1,-1,-1,1,1,-1,-1,-1,-1],"vocal_parts":1,"song_scroll_speed":2300,"bank":"sfx/tambourine_bank.milo","anim_tempo":64,"preview":[48878,78878],"rank_drum":209,"rank_guitar":168,"rank_bass":146,"rank_vocals":144,"rank_band":181,"genre":"emo","vocal_gender":"male","format":10,"version":30,"album_art":true,"album_name":"We the Kings","album_track_number":3,"year_released":2007,"rating":1,"game_origin":"lego","base_points":628492,"encoding":"latin1","drum_bank":"sfx/rb2_kit01_bank.milo","vocal_tonic_note":2,"song_tonality":0,"extra_authoring":["disc_update"],"upgrade_version":1,"rank_keys":327,"rank_real_keys":327,"rank_real_guitar":168,"rank_real_bass":146,"real_guitar_tuning":[0,0,0,0,0,0],"real_bass_tuning":[0,0,0,0],"keys_author":"Linos Melendi","song_length":223636},{"id":"crash","name":"Crash","artist":"The Primitives","fake":false,"master":true,"context":939,"song_id":756,"songname":"crash","tracks_count":[6,1,2,2,0,2],"pans":[-1,1,-1,1,-1,1,0,-1,1,-1,1,-1,1],"vols":[-0.5,-0.5,-1.5,-1.5,-2,-2,-2.5,-3,-3,-3,-3,-1.5,-1.5],"cores":[-1,-1,-1,-1,-1,-1,-1,1,1,-1,-1,-1,-1],"vocal_parts":3,"song_scroll_speed":2300,"bank":"sfx/tambourine_bank.milo","anim_tempo":64,"preview":[105790,135790],"rank_drum":225,"rank_guitar":213,"rank_bass":130,"rank_vocals":133,"rank_band":169,"genre":"poprock","vocal_gender":"female","format":10,"version":3,"album_art":true,"album_name":"Lovely","album_track_number":1,"year_released":1988,"rating":1,"game_origin":"lego","base_points":466292,"encoding":"latin1","drum_bank":"sfx/rb2_kit01_bank.milo","vocal_tonic_note":11,"song_tonality":0,"extra_authoring":["disc_update"],"song_length":163636,"loading_phrase":"In 1994, the song was featured on the \"Dumb & Dumber\" movie soundtrack as \"Crash - The '95 Mix.\" This remix included additional guitars, percussion, organ and backing vocals - none of which were performed by any of The Primitives."},{"id":"crocodilerock","name":"Crocodile Rock","artist":"Elton John","fake":false,"master":true,"context":925,"song_id":757,"songname":"crocodilerock","tracks_count":[2,1,2,2,2,0],"pans":[-1,1,0,-1,1,-1,1,-1,1],"vols":[-1,-1,-2.5,-4,-4,-2,-2,-4.5,-4.5],"cores":[-1,-1,-1,1,1,-1,-1,-1,-1],"vocal_parts":1,"song_scroll_speed":2300,"bank":"sfx/tambourine_bank.milo","anim_tempo":32,"preview":[66000,96000],"rank_drum":156,"rank_guitar":212,"rank_bass":175,"rank_vocals":234,"rank_band":163,"genre":"poprock","vocal_gender":"male","format":10,"version":30,"album_art":true,"album_name":"Don't Shoot Me I'm Only the Piano Player","album_track_number":9,"year_released":1973,"rating":1,"game_origin":"lego","base_points":614372,"encoding":"latin1","drum_bank":"sfx/rb2_kit01_bank.milo","vocal_tonic_note":7,"song_tonality":0,"extra_authoring":["disc_update"],"rank_keys":269,"rank_real_keys":327,"keys_author":"TheSheepQueen","song_length":222727,"loading_phrase":"Bob the Builder included a cover of \"Crocodile Rock\" on his debut album in 2001."},{"id":"dig","name":"Dig","artist":"Incubus","fake":false,"master":true,"context":933,"song_id":758,"songname":"dig","tracks_count":[6,1,2,2,2,0],"pans":[-1,1,-1,1,-1,1,0,-1,1,-1,1,-1,1],"vols":[-1.4,-1.4,-2.7,-2.7,-3.5,-3.5,-0.9,-4.2,-4.2,-1,-1,-3,-3],"cores":[-1,-1,-1,-1,-1,-1,-1,1,1,-1,-1,-1,-1],"vocal_parts":1,"hopo_threshold":90,"song_scroll_speed":2300,"bank":"sfx/tambourine_bank.milo","anim_tempo":16,"preview":[66200,96030],"rank_drum":188,"rank_guitar":215,"rank_bass":191,"rank_vocals":255,"rank_band":193,"genre":"alternative","vocal_gender":"male","format":10,"version":30,"album_art":true,"album_name":"Light Grenades","album_track_number":3,"year_released":2006,"rating":1,"game_origin":"lego","base_points":510027,"encoding":"latin1","drum_bank":"sfx/rb2_kit01_bank.milo","vocal_tonic_note":1,"song_tonality":1,"extra_authoring":["disc_update"],"rank_keys":96,"rank_real_keys":99,"keys_author":"StackOverflow0x & sageamagoo","song_length":265000,"solo":["guitar"],"loading_phrase":"The Incubus album \"Light Grenades\" debuted at Number 1 on the Billboard 200, selling 165,000 copies in the U.S. in its first week."},{"id":"dreamingofyou","name":"Dreaming of You","artist":"The Coral","fake":false,"master":true,"context":915,"song_id":759,"songname":"dreamingofyou","tracks_count":[5,1,2,2,2,0],"pans":[0,-1,1,-1,1,0,-1,1,-1,1,-1,1],"vols":[-1,-2.5,-2.5,-4,-4,-4,-2.7,-2.7,-3.3,-3.3,-3.5,-3.5],"cores":[-1,-1,-1,-1,-1,-1,1,1,-1,-1,-1,-1],"vocal_parts":1,"hopo_threshold":250,"song_scroll_speed":2300,"bank":"sfx/tambourine_bank.milo","anim_tempo":64,"preview":[17647,47647],"rank_drum":127,"rank_guitar":145,"rank_bass":182,"rank_vocals":153,"rank_band":149,"genre":"indierock","vocal_gender":"male","format":10,"version":30,"album_art":true,"album_name":"The Coral","album_track_number":4,"year_released":2002,"rating":1,"game_origin":"lego","base_points":297379,"encoding":"latin1","drum_bank":"sfx/rb2_kit01_bank.milo","vocal_tonic_note":9,"song_tonality":1,"extra_authoring":["disc_update"],"rank_keys":170,"rank_real_keys":170,"keys_author":"TheSheepQueen","song_length":140909,"solo":["guitar","vocal_percussion"]},{"id":"everylittlething","name":"Every Little Thing She Does Is Magic","artist":"The Police","fake":false,"master":true,"context":928,"song_id":760,"songname":"everylittlething","tracks_count":[5,1,2,2,2,0],"pans":[0,-1,1,-1,1,0,-1,1,-1,1,-1,1],"vols":[-1,-3,-3,-3,-3,-2,-5,-5,-3,-3,-3,-3],"cores":[-1,-1,-1,-1,-1,-1,1,1,-1,-1,-1,-1],"vocal_parts":1,"song_scroll_speed":2300,"bank":"sfx/tambourine_bank.milo","anim_tempo":16,"preview":[40042,70042],"rank_drum":306,"rank_guitar":190,"rank_bass":181,"rank_vocals":256,"rank_band":251,"genre":"new_wave","vocal_gender":"male","format":10,"version":30,"album_art":true,"album_name":"Ghost in the Machine","album_track_number":2,"year_released":1981,"rating":1,"tuning_offset_cents":43,"game_origin":"lego","base_points":672134,"encoding":"latin1","drum_bank":"sfx/rb2_kit01_bank.milo","vocal_tonic_note":2,"song_tonality":0,"extra_authoring":["disc_update"],"upgrade_version":1,"rank_keys":318,"rank_real_keys":363,"keys_author":"BowlsforRick, SonicSBL","song_length":270909},{"id":"freefallin","name":"Free Fallin'","artist":"Tom Petty","fake":false,"master":true,"context":924,"song_id":761,"songname":"freefallin","tracks_count":[5,1,2,2,2,0],"pans":[0,-1,1,-1,1,0,-1,1,-1,1,-1,1],"vols":[-0.5,-1,-1,-3.5,-3.5,-3,-4.5,-4.5,-2.5,-2.5,-5,-5],"cores":[-1,-1,-1,-1,-1,-1,1,1,-1,-1,-1,-1],"vocal_parts":1,"song_scroll_speed":2300,"bank":"sfx/tambourine_bank.milo","anim_tempo":16,"preview":[67152,97152],"rank_drum":117,"rank_guitar":166,"rank_bass":213,"rank_vocals":129,"rank_band":146,"genre":"rock","vocal_gender":"male","format":10,"version":30,"album_art":true,"album_name":"Full Moon Fever","album_track_number":1,"year_released":1989,"rating":1,"game_origin":"lego","base_points":510626,"encoding":"latin1","drum_bank":"sfx/rb2_kit01_bank.milo","vocal_tonic_note":5,"song_tonality":0,"extra_authoring":["disc_update"],"rank_keys":1,"rank_real_keys":1,"keys_author":"FujiSkunk","song_length":265909},{"id":"ghostbusters","name":"Ghostbusters","artist":"Ray Parker Jr.","fake":false,"master":true,"context":950,"song_id":762,"songname":"ghostbusters","tracks_count":[6,1,2,2,2,0,2],"pans":[-1,1,-1,1,-1,1,0,-1,1,-1,1,-1,1,-2.5,2.5],"vols":[-2.5,-2.5,-2,-2,-2.5,-2.5,-1,-3.5,-3.5,-2,-2,-2.5,-2.5,-4,-4],"cores":[-1,-1,-1,-1,-1,-1,-1,1,1,-1,-1,-1,-1,-1,-1],"vocal_parts":1,"song_scroll_speed":2300,"bank":"sfx/tambourine_bank.milo","anim_tempo":32,"preview":[31500,61500],"rank_drum":186,"rank_guitar":224,"rank_bass":186,"rank_vocals":141,"rank_band":192,"genre":"popdanceelectronic","vocal_gender":"male","format":10,"version":30,"album_art":true,"album_name":"Ghostbusters: Original Soundtrack","album_track_number":1,"year_released":1984,"rating":1,"game_origin":"lego","base_points":502324,"encoding":"latin1","drum_bank":"sfx/rb2_kit01_bank.milo","vocal_tonic_note":11,"song_tonality":1,"extra_authoring":["disc_update"],"rank_keys":170,"rank_real_keys":211,"keys_author":"TheSheepQueen","upgrade_version":1,"rank_real_guitar":357,"rank_real_bass":345,"real_guitar_tuning":[0,0,0,0,0,0],"real_bass_tuning":[0,0,0,0],"strings_author":"RK","song_length":251363,"solo":["drum"]},{"id":"girlsandboys","name":"Girls & Boys","artist":"Good Charlotte","fake":false,"master":true,"context":937,"song_id":763,"songname":"girlsandboys","tracks_count":[5,2,2,2,0,2,2],"pans":[0,-1,1,-1,1,-1,1,-1,1,-1,1,-1,1,-2.5,2.5],"vols":[-1,-3,-3,-5,-5,-4.5,-4.5,-4.5,-4.5,-2.5,-2.5,-5,-5,-4.5,-4.5],"cores":[-1,-1,-1,-1,-1,-1,-1,1,1,-1,-1,-1,-1,-1,-1],"vocal_parts":2,"song_scroll_speed":2300,"bank":"sfx/tambourine_bank.milo","anim_tempo":32,"preview":[22198,52198],"rank_drum":175,"rank_guitar":211,"rank_bass":128,"rank_vocals":207,"rank_band":168,"genre":"punk","vocal_gender":"male","format":10,"version":3,"album_art":true,"album_name":"The Young and the Hopeless","album_track_number":6,"year_released":2002,"rating":1,"game_origin":"lego","base_points":465985,"encoding":"latin1","drum_bank":"sfx/rb2_kit01_bank.milo","vocal_tonic_note":3,"song_tonality":0,"extra_authoring":["disc_update"],"song_length":190000,"solo":["guitar"]},{"id":"grace","name":"Grace","artist":"Supergrass","fake":false,"master":true,"context":943,"song_id":764,"songname":"grace","tracks_count":[4,1,2,2,2,0],"pans":[0,0,-1,1,0,-1,1,-1,1,-1,1],"vols":[-0.5,-0.5,-3,-3,-2.5,-2.5,-2.5,-2,-2,-2.2,-2.2],"cores":[-1,-1,-1,-1,-1,1,1,-1,-1,-1,-1],"vocal_parts":1,"song_scroll_speed":2300,"bank":"sfx/tambourine_bank.milo","anim_tempo":32,"preview":[20224,50224],"rank_drum":247,"rank_guitar":219,"rank_bass":207,"rank_vocals":134,"rank_band":213,"genre":"alternative","vocal_gender":"male","format":10,"version":30,"album_art":true,"album_name":"Life on Other Planets","album_track_number":9,"year_released":2002,"rating":1,"game_origin":"lego","base_points":391678,"encoding":"latin1","drum_bank":"sfx/rb2_kit01_bank.milo","vocal_tonic_note":9,"song_tonality":0,"extra_authoring":["disc_update"],"rank_keys":272,"rank_real_keys":272,"keys_author":"JohnSmith, SonicSBL","song_length":154545,"loading_phrase":"The Supergrass single \"Grace\" features the lyric \"Save the money for the children\". This was inspired by the daughter of Squeeze's Chris Difford, who was running around the studio with a moneybox bearing these same words."},{"id":"iwantyouback","name":"I Want You Back","artist":"The Jackson 5","fake":false,"master":true,"context":931,"song_id":765,"songname":"iwantyouback","tracks_count":[2,2,2,2,2,0],"pans":[-1,1,-1,1,-1,1,-1,1,-1,1],"vols":[-1,-1,-4.5,-4.5,-1.5,-1.5,-2,-2,-4,-4],"cores":[-1,-1,-1,-1,1,1,-1,-1,-1,-1],"vocal_parts":1,"song_scroll_speed":2300,"bank":"sfx/tambourine_bank.milo","anim_tempo":32,"preview":[44494,73285],"rank_drum":220,"rank_guitar":252,"rank_bass":264,"rank_vocals":355,"rank_band":241,"genre":"poprock","vocal_gender":"male","format":10,"version":30,"album_art":true,"album_name":"Diana Ross Presents The Jackson 5","album_track_number":3,"year_released":1969,"rating":1,"game_origin":"lego","base_points":450018,"encoding":"latin1","drum_bank":"sfx/rb2_kit01_bank.milo","vocal_tonic_note":8,"song_tonality":0,"extra_authoring":["disc_update"],"rank_keys":269,"rank_real_keys":269,"keys_author":"FujiSkunk","song_length":205454},{"id":"intoodeep","name":"In Too Deep","artist":"Sum 41","fake":false,"master":true,"context":932,"song_id":766,"songname":"intoodeep","tracks_count":[5,1,2,2,0,2],"pans":[0,-1,1,-1,1,0,-1,1,-1,1,-1,1],"vols":[-0.5,-1,-1,-4,-4,-2.5,-2.5,-2.5,-3,-3,-3,-3],"cores":[-1,-1,-1,-1,-1,-1,1,1,-1,-1,-1,-1],"vocal_parts":3,"song_scroll_speed":2300,"bank":"sfx/tambourine_bank.milo","anim_tempo":32,"preview":[28571,57142],"rank_drum":232,"rank_guitar":321,"rank_bass":230,"rank_vocals":148,"rank_band":279,"genre":"punk","vocal_gender":"male","format":10,"version":3,"album_art":true,"album_name":"All Killer No Filler","album_track_number":7,"year_released":2001,"rating":1,"game_origin":"lego","base_points":525801,"encoding":"latin1","drum_bank":"sfx/rb2_kit01_bank.milo","vocal_tonic_note":4,"song_tonality":0,"extra_authoring":["disc_update"],"song_length":211818,"solo":["guitar"]},{"id":"kungfufighting","name":"Kung Fu Fighting","artist":"Carl Douglas","fake":false,"master":true,"context":948,"song_id":768,"songname":"kungfufighting","tracks_count":[5,2,2,2,2,0],"pans":[0,-1,1,-1,1,-1,1,-1,1,-1,1,-1,1],"vols":[-1,-2,-2,-1,-1,-4,-4,-2.5,-2.5,-1,-1,-2,-2],"cores":[-1,-1,-1,-1,-1,-1,-1,1,1,-1,-1,-1,-1],"vocal_parts":1,"song_scroll_speed":2300,"bank":"sfx/handclap_bank.milo","anim_tempo":32,"preview":[104629,134629],"rank_drum":254,"rank_guitar":335,"rank_bass":173,"rank_vocals":234,"rank_band":234,"genre":"rbsoulfunk","vocal_gender":"male","format":10,"version":30,"album_art":true,"year_released":1974,"rating":1,"game_origin":"lego","base_points":549897,"encoding":"latin1","drum_bank":"sfx/rb2_kit01_bank.milo","vocal_tonic_note":2,"song_tonality":0,"extra_authoring":["disc_update"],"rank_keys":211,"rank_real_keys":269,"keys_author":"TheSheepQueen","upgrade_version":1,"rank_real_guitar":188,"rank_real_bass":88,"real_guitar_tuning":[0,0,0,0,0,0],"real_bass_tuning":[0,0,0,0],"strings_author":"RK","song_length":201363,"loading_phrase":"The popularity of \"Kung Fu Fighting\" led to a dance craze called \"The Kung Fu Step\" in UK & US discotheques."},{"id":"letsdance","name":"Let's Dance","artist":"David Bowie","fake":false,"master":true,"context":947,"song_id":769,"songname":"letsdance","tracks_count":[6,1,2,2,2,0],"pans":[-1,1,-1,1,-1,1,0,-1,1,-1,1,-1,1],"vols":[-1,-1,-2,-2,-2,-2,-4,-3,-3,-3,-3,-3.5,-3.5],"cores":[-1,-1,-1,-1,-1,-1,-1,1,1,-1,-1,-1,-1],"vocal_parts":1,"song_scroll_speed":2300,"bank":"sfx/handclap_bank.milo","anim_tempo":32,"preview":[27863,56563],"rank_drum":160,"rank_guitar":144,"rank_bass":153,"rank_vocals":145,"rank_band":145,"genre":"glam","vocal_gender":"male","format":10,"version":30,"album_art":true,"album_name":"Let's Dance","album_track_number":3,"year_released":1983,"rating":1,"game_origin":"lego","base_points":455341,"encoding":"latin1","drum_bank":"sfx/rb2_kit01_bank.milo","vocal_tonic_note":10,"song_tonality":1,"extra_authoring":["disc_update"],"rank_keys":153,"rank_real_keys":153,"keys_author":"Linos Melendi","song_length":295000,"solo":["guitar"]},{"id":"lifeisahighway","name":"Life Is a Highway","artist":"Rascal Flatts","fake":false,"master":true,"context":921,"song_id":770,"songname":"lifeisahighway","tracks_count":[4,1,2,2,2,0],"pans":[0,0,-1,1,0,-1,1,-1,1,-1,1],"vols":[-1.5,-2.5,-4,-4,-2,-4,-4,-4,-4,-4,-4],"cores":[-1,-1,-1,-1,-1,1,1,-1,-1,-1,-1],"vocal_parts":1,"song_scroll_speed":2300,"bank":"sfx/tambourine_bank.milo","anim_tempo":32,"preview":[43000,73000],"rank_drum":221,"rank_guitar":237,"rank_bass":281,"rank_vocals":329,"rank_band":253,"genre":"country","vocal_gender":"male","format":10,"version":30,"album_art":true,"album_name":"Me and My Gang","album_track_number":14,"year_released":2006,"rating":1,"game_origin":"lego","base_points":626958,"encoding":"latin1","drum_bank":"sfx/rb2_kit01_bank.milo","vocal_tonic_note":5,"song_tonality":0,"extra_authoring":["disc_update"],"rank_keys":370,"rank_real_keys":370,"keys_author":"SonicSBL","song_length":254545,"solo":["guitar"]},{"id":"makemesmile","name":"Make Me Smile (Come Up and See Me)","artist":"Steve Harley & Cockney Rebel","fake":false,"master":true,"context":913,"song_id":771,"songname":"makemesmile","tracks_count":[4,1,2,2,2,0],"pans":[0,0,-1,1,0,-1,1,-1,1,-1,1],"vols":[-1.5,-1.5,-5,-5,-4,-3,-3,-2.5,-2.5,-4,-4],"cores":[-1,-1,-1,-1,-1,1,1,-1,-1,-1,-1],"vocal_parts":1,"song_scroll_speed":2300,"bank":"sfx/tambourine_bank.milo","anim_tempo":32,"preview":[69217,97469],"rank_drum":185,"rank_guitar":218,"rank_bass":190,"rank_vocals":331,"rank_band":230,"genre":"rock","vocal_gender":"male","format":10,"version":30,"album_art":true,"album_name":"The Best Years of Our Lives","album_track_number":6,"year_released":1975,"rating":1,"game_origin":"lego","base_points":600118,"encoding":"latin1","drum_bank":"sfx/rb2_kit01_bank.milo","vocal_tonic_note":7,"song_tonality":0,"extra_authoring":["disc_update"],"rank_keys":320,"rank_real_keys":310,"keys_author":"SonicSBL","song_length":249090,"solo":["guitar","vocal_percussion"],"loading_phrase":"Despite the seemingly happy nature of his biggest hit \"Make Me Smile (Come Up and See Me)\", Steve Harley revealed that the lyrics were in fact a reproach to his former bandmates, whom he felt had abandoned him."},{"id":"monster","name":"Monster","artist":"The Automatic","fake":false,"master":true,"context":938,"song_id":772,"songname":"monster","tracks_count":[5,1,2,2,2,0],"pans":[0,-1,1,-1,1,0,-1,1,-1,1,-1,1],"vols":[-1,-1.5,-1.5,-4,-4,-2.5,-2.5,-2.5,-2,-2,-3.5,-3.5],"cores":[-1,-1,-1,-1,-1,-1,1,1,-1,-1,-1,-1],"vocal_parts":1,"song_scroll_speed":2300,"bank":"sfx/tambourine_bank.milo","anim_tempo":32,"preview":[30478,59335],"rank_drum":297,"rank_guitar":261,"rank_bass":179,"rank_vocals":143,"rank_band":233,"genre":"alternative","vocal_gender":"male","format":10,"version":30,"album_art":true,"album_name":"Not Accepted Anywhere","album_track_number":5,"year_released":2006,"rating":1,"game_origin":"lego","base_points":586214,"encoding":"latin1","drum_bank":"sfx/rb2_kit01_bank.milo","vocal_tonic_note":4,"song_tonality":1,"extra_authoring":["disc_update"],"upgrade_version":1,"rank_keys":240,"rank_real_keys":180,"rank_real_guitar":377,"rank_real_bass":297,"real_guitar_tuning":[0,0,0,0,0,0],"real_bass_tuning":[0,0,0,0],"strings_author":"RK","keys_author":"BowlsforRick","song_length":228181,"solo":["guitar","vocal_percussion"]},{"id":"naive","name":"Naïve","artist":"The Kooks","fake":false,"master":true,"context":940,"song_id":773,"songname":"naive","tracks_count":[5,1,2,2,2,0],"pans":[0,-1,1,-1,1,0,-1,1,-1,1,-1,1],"vols":[-0.5,-1.2,-1.2,-3,-3,-2.7,-3.7,-3.7,-1,-1,-5,-5],"cores":[-1,-1,-1,-1,-1,-1,1,1,-1,-1,-1,-1],"vocal_parts":1,"song_scroll_speed":2300,"bank":"sfx/tambourine_bank.milo","anim_tempo":32,"preview":[85774,115774],"rank_drum":273,"rank_guitar":259,"rank_bass":240,"rank_vocals":239,"rank_band":242,"genre":"indierock","vocal_gender":"male","format":10,"version":30,"album_art":true,"album_name":"Inside In/Inside Out","album_track_number":9,"year_released":2006,"rating":1,"game_origin":"lego","base_points":563540,"encoding":"latin1","drum_bank":"sfx/rb2_kit01_bank.milo","vocal_tonic_note":8,"song_tonality":1,"extra_authoring":["disc_update"],"rank_keys":82,"rank_real_keys":82,"keys_author":"BowlsforRick","song_length":207727},{"id":"realwildchild","name":"Real Wild Child","artist":"Everlife","fake":false,"master":true,"context":911,"song_id":774,"songname":"realwildchild","tracks_count":[2,1,2,2,0,2],"pans":[-1,1,0,-1,1,-1,1,-1,1],"vols":[-1,-1,-4,-5.5,-5.5,-3.7,-3.7,-6,-6],"cores":[-1,-1,-1,1,1,-1,-1,-1,-1],"vocal_parts":3,"song_scroll_speed":2300,"bank":"sfx/tambourine_bank.milo","anim_tempo":32,"preview":[46718,76718],"rank_drum":358,"rank_guitar":280,"rank_bass":190,"rank_vocals":440,"rank_band":285,"genre":"poprock","vocal_gender":"female","format":10,"version":3,"album_art":true,"album_name":"Everlife","album_track_number":11,"year_released":2007,"rating":1,"game_origin":"lego","base_points":592223,"encoding":"latin1","drum_bank":"sfx/rb2_kit01_bank.milo","vocal_tonic_note":5,"song_tonality":0,"extra_authoring":["disc_update"],"upgrade_version":1,"rank_real_guitar":327,"rank_real_bass":367,"real_guitar_tuning":[0,0,0,0,0,0],"real_bass_tuning":[-2,0,0,0],"strings_author":"RK","song_length":199090,"solo":["drum"]},{"id":"rideawhiteswan","name":"Ride a White Swan","artist":"T. Rex","fake":false,"master":true,"context":936,"song_id":775,"songname":"rideawhiteswan","tracks_count":[2,1,2,2,0,2],"pans":[-1,1,0,-1,1,-1,1,-1,1],"vols":[-1,-1,-3,-3,-3,-4,-4,-3,-3],"cores":[-1,-1,-1,1,1,-1,-1,-1,-1],"vocal_parts":3,"song_scroll_speed":2300,"bank":"sfx/tambourine_bank.milo","anim_tempo":64,"preview":[27200,51500],"rank_drum":91,"rank_guitar":222,"rank_bass":98,"rank_vocals":119,"rank_band":134,"genre":"glam","vocal_gender":"male","format":10,"version":3,"album_art":true,"album_name":"","album_track_number":1,"year_released":1972,"rating":1,"tuning_offset_cents":10,"game_origin":"lego","base_points":276162,"encoding":"latin1","drum_bank":"sfx/rb2_kit01_bank.milo","vocal_tonic_note":8,"song_tonality":0,"extra_authoring":["disc_update"],"song_length":147272,"solo":["guitar","vocal_percussion"],"loading_phrase":"Originally a British folk-rock combo called Tyrannosaurus Rex, the band changed their name to T. Rex and released the single \"Ride a White Swan\". They quickly became one of the primary forces of the Glam Rock movement in the 1970's."},{"id":"rooftops","name":"Rooftops (A Liberation Broadcast)","artist":"Lostprophets","fake":false,"master":true,"context":927,"song_id":776,"songname":"rooftops","tracks_count":[5,1,2,2,2,0],"pans":[0,-1,1,-1,1,0,-1,1,-1,1,-1,1],"vols":[-0.5,-3,-3,-4.5,-4.5,-3,-5,-5,-2,-2,-5,-5],"cores":[-1,-1,-1,-1,-1,-1,1,1,-1,-1,-1,-1],"vocal_parts":1,"song_scroll_speed":2300,"bank":"sfx/tambourine_bank.milo","anim_tempo":16,"preview":[63994,93994],"rank_drum":247,"rank_guitar":188,"rank_bass":185,"rank_vocals":159,"rank_band":190,"genre":"rock","vocal_gender":"male","format":10,"version":29,"album_art":true,"album_name":"Liberation Transmission","album_track_number":4,"year_released":2006,"rating":1,"game_origin":"lego","base_points":680976,"encoding":"latin1","drum_bank":"sfx/rb2_kit01_bank.milo","vocal_tonic_note":7,"song_tonality":0,"extra_authoring":["disc_update"],"upgrade_version":1,"rank_keys":182,"rank_real_keys":182,"rank_real_guitar":276,"rank_real_bass":212,"real_guitar_tuning":[-2,0,0,0,0,0],"real_bass_tuning":[-2,0,0,0],"strings_author":"MatthNerd","keys_author":"SonicSBL","song_length":251363,"solo":["guitar"]},{"id":"ruby","name":"Ruby","artist":"Kaiser Chiefs","fake":false,"master":true,"context":935,"song_id":777,"songname":"ruby","tracks_count":[5,1,2,2,2,0,2],"pans":[0,-1,1,-1,1,0,-1,1,-1,1,-1,1,-2.5,2.5],"vols":[-1,-2,-2,-3,-3,-4.5,-4,-4,-3,-3,-5,-5,-3,-3],"cores":[-1,-1,-1,-1,-1,-1,1,1,-1,-1,-1,-1,-1,-1],"vocal_parts":1,"song_scroll_speed":2300,"bank":"sfx/tambourine_bank.milo","anim_tempo":16,"preview":[43432,72288],"rank_drum":263,"rank_guitar":180,"rank_bass":147,"rank_vocals":151,"rank_band":200,"genre":"indierock","vocal_gender":"male","format":10,"version":30,"album_art":true,"album_name":"Yours Truly, Angry Mob","album_track_number":1,"year_released":2007,"rating":1,"game_origin":"lego","base_points":505299,"encoding":"latin1","drum_bank":"sfx/rb2_kit01_bank.milo","vocal_tonic_note":10,"song_tonality":1,"extra_authoring":["disc_update"],"rank_keys":170,"rank_real_keys":170,"keys_author":"TheSheepQueen","upgrade_version":1,"rank_real_guitar":242,"rank_real_bass":184,"real_guitar_tuning":[0,0,0,0,0,0],"real_bass_tuning":[0,0,0,0],"strings_author":"WarGod, Carl Mylo","song_length":215000,"solo":["guitar"]},{"id":"shortandsweet","name":"Short and Sweet","artist":"Spinal Tap","fake":false,"master":true,"context":907,"song_id":778,"songname":"shortandsweet","tracks_count":[4,1,2,2,2,0],"pans":[0,0,-1,1,0,-1,1,-1,1,-1,1],"vols":[-2,-1,-3,-3,-4,-3.7,-3.7,-2.5,-2.5,-3.5,-3.5],"cores":[-1,-1,-1,-1,-1,1,1,-1,-1,-1,-1],"vocal_parts":1,"song_scroll_speed":2300,"bank":"sfx/handclap_bank.milo","anim_tempo":64,"preview":[127974,157974],"rank_drum":311,"rank_guitar":304,"rank_bass":304,"rank_vocals":157,"rank_band":321,"genre":"metal","vocal_gender":"male","format":10,"version":29,"album_art":true,"album_name":"Back from the Dead","album_track_number":18,"year_released":2009,"rating":1,"game_origin":"lego","base_points":782510,"encoding":"latin1","drum_bank":"sfx/rb2_kit01_bank.milo","vocal_tonic_note":4,"song_tonality":1,"extra_authoring":["disc_update"],"rank_keys":451,"rank_real_keys":462,"keys_author":"SonicSBL","song_length":399545,"solo":["guitar","vocal_percussion"]},{"id":"sowhat","name":"So What","artist":"P!nk","fake":false,"master":true,"context":934,"song_id":779,"songname":"sowhat","tracks_count":[6,1,2,2,2,0,2],"pans":[-1,1,-1,1,-1,1,0,-1,1,-1,1,-1,1,-2.5,2.5],"vols":[-2,-2,-2,-2,-3,-3,-5,-6,-6,-3,-3,-3.5,-3.5,-3.5,-3.5],"cores":[-1,-1,-1,-1,-1,-1,-1,1,1,-1,-1,-1,-1,-1,-1],"vocal_parts":1,"song_scroll_speed":2300,"bank":"sfx/tambourine_bank.milo","anim_tempo":32,"preview":[37523,67523],"rank_drum":198,"rank_guitar":181,"rank_bass":142,"rank_vocals":218,"rank_band":201,"genre":"poprock","vocal_gender":"female","format":10,"version":30,"album_art":true,"album_name":"Funhouse","album_track_number":1,"year_released":2008,"rating":1,"game_origin":"lego","base_points":543399,"encoding":"latin1","drum_bank":"sfx/rb2_kit01_bank.milo","vocal_tonic_note":6,"song_tonality":1,"extra_authoring":["disc_update"],"rank_keys":211,"rank_real_keys":211,"keys_author":"TheSheepQueen","song_length":224090,"solo":["guitar"]},{"id":"song2","name":"Song 2","artist":"Blur","fake":false,"master":true,"context":944,"song_id":780,"songname":"song2","tracks_count":[6,1,2,2,0,1,2],"pans":[-1,1,-1,1,-1,1,0,-1,1,-1,1,0,-2.5,2.5],"vols":[-3,-3,-3.5,-3.5,-3.5,-3.5,-1.5,-3.5,-3.5,-3.5,-3.5,-4,-3,-3],"cores":[-1,-1,-1,-1,-1,-1,-1,1,1,-1,-1,-1,-1,-1],"vocal_parts":2,"song_scroll_speed":2300,"bank":"sfx/tambourine_bank.milo","anim_tempo":32,"preview":[11000,41000],"rank_drum":187,"rank_guitar":151,"rank_bass":122,"rank_vocals":115,"rank_band":140,"genre":"alternative","vocal_gender":"male","format":10,"version":3,"album_art":true,"album_name":"Blur","album_track_number":2,"year_released":1997,"rating":1,"game_origin":"lego","base_points":267423,"encoding":"latin1","drum_bank":"sfx/rb2_kit01_bank.milo","vocal_tonic_note":5,"song_tonality":1,"extra_authoring":["disc_update"],"upgrade_version":1,"rank_real_guitar":99,"rank_real_bass":129,"real_guitar_tuning":[0,0,0,0,0,0],"real_bass_tuning":[0,0,0,0],"strings_author":"RK","song_length":132272,"loading_phrase":"Originally called \"Song 2\" because Blur had yet to think of a name, it was also the second track on the album, was the second single from the album to be released, and is exactly two minutes and two seconds long. jnack was in LEGO Rock Band btw."},{"id":"stumbleandfall","name":"Stumble and Fall","artist":"Razorlight","fake":false,"master":true,"context":926,"song_id":781,"songname":"stumbleandfall","tracks_count":[5,1,2,2,0,2],"pans":[0,-1,1,-1,1,0,-1,1,-1,1,-1,1],"vols":[-2.5,-3.5,-3.5,-4.5,-4.5,-1.5,-3,-3,-2,-2,-2,-2],"cores":[-1,-1,-1,-1,-1,-1,1,1,-1,-1,-1,-1],"vocal_parts":3,"song_scroll_speed":2300,"bank":"sfx/tambourine_bank.milo","anim_tempo":64,"preview":[92531,122531],"rank_drum":335,"rank_guitar":223,"rank_bass":176,"rank_vocals":202,"rank_band":249,"genre":"rock","vocal_gender":"male","format":10,"version":3,"album_art":true,"album_name":"Up All Night","album_track_number":9,"year_released":2004,"rating":1,"game_origin":"lego","base_points":495875,"encoding":"latin1","drum_bank":"sfx/rb2_kit01_bank.milo","vocal_tonic_note":0,"song_tonality":0,"extra_authoring":["disc_update"],"song_length":190000,"solo":["guitar"]},{"id":"suddenlyisee","name":"Suddenly I See","artist":"KT Tunstall","fake":false,"master":true,"context":941,"song_id":782,"songname":"suddenlyisee","tracks_count":[2,2,2,2,0,2],"pans":[-1,1,-1,1,-1,1,-1,1,-1,1],"vols":[-1,-1,-2.3,-2.3,-2,-2,-2.5,-2.5,-2,-2],"cores":[-1,-1,-1,-1,1,1,-1,-1,-1,-1],"vocal_parts":3,"song_scroll_speed":2300,"bank":"sfx/tambourine_bank.milo","anim_tempo":16,"preview":[43932,73932],"rank_drum":330,"rank_guitar":253,"rank_bass":153,"rank_vocals":249,"rank_band":283,"genre":"rock","vocal_gender":"female","format":10,"version":3,"album_art":true,"album_name":"Eye to the Telescope","album_track_number":9,"year_released":2004,"rating":1,"game_origin":"lego","base_points":521778,"encoding":"latin1","drum_bank":"sfx/rb2_kit01_bank.milo","vocal_tonic_note":2,"song_tonality":0,"extra_authoring":["disc_update"],"song_length":207727},{"id":"summerof69","name":"Summer of '69","artist":"Bryan Adams","fake":false,"master":true,"context":910,"song_id":783,"songname":"summerof69","tracks_count":[5,1,2,2,2,0],"pans":[0,-1,1,-1,1,0,-1,1,-1,1,-1,1],"vols":[-1,-2,-2,-3,-3,-5,-3,-3,-2.5,-2.5,-5,-5],"cores":[-1,-1,-1,-1,-1,-1,1,1,-1,-1,-1,-1],"vocal_parts":1,"song_scroll_speed":2300,"bank":"sfx/tambourine_bank.milo","anim_tempo":32,"preview":[30748,59156],"rank_drum":197,"rank_guitar":134,"rank_bass":169,"rank_vocals":182,"rank_band":148,"genre":"rock","vocal_gender":"male","format":10,"version":30,"album_art":true,"album_name":"Reckless","album_track_number":7,"year_released":1984,"rating":1,"game_origin":"lego","base_points":508213,"encoding":"latin1","drum_bank":"sfx/rb2_kit01_bank.milo","vocal_tonic_note":2,"song_tonality":0,"extra_authoring":["disc_update"],"rank_keys":134,"rank_real_keys":134,"keys_author":"DVDSmith","song_length":235909,"solo":["guitar"],"loading_phrase":"'Summer of '69' has appeared on all of Bryan Adams' compilation albums."},{"id":"swingswing","name":"Swing, Swing","artist":"The All-American Rejects","fake":false,"master":true,"context":920,"song_id":784,"songname":"swingswing","tracks_count":[5,1,2,2,2,0],"pans":[0,-1,1,-1,1,0,-1,1,-1,1,-1,1],"vols":[-1,-2.5,-2.5,-5,-5,-4.5,-3.5,-3.5,-3.2,-3.2,-5,-5],"cores":[-1,-1,-1,-1,-1,-1,1,1,-1,-1,-1,-1],"vocal_parts":1,"song_scroll_speed":2300,"bank":"sfx/tambourine_bank.milo","anim_tempo":32,"preview":[70774,99567],"rank_drum":126,"rank_guitar":137,"rank_bass":144,"rank_vocals":181,"rank_band":147,"genre":"emo","vocal_gender":"male","format":10,"version":30,"album_art":true,"album_name":"The All-American Rejects","album_track_number":3,"year_released":2003,"rating":1,"game_origin":"lego","base_points":554810,"encoding":"latin1","drum_bank":"sfx/rb2_kit01_bank.milo","vocal_tonic_note":7,"song_tonality":0,"extra_authoring":["disc_update"],"rank_keys":170,"rank_real_keys":211,"keys_author":"TheSheepQueen","song_length":241363,"solo":["guitar"]},{"id":"thefinalcountdown","name":"The Final Countdown","artist":"Europe","fake":false,"master":true,"context":942,"song_id":785,"songname":"thefinalcountdown","tracks_count":[6,1,2,2,2,0,2],"pans":[-1,1,-1,1,-1,1,0,-1,1,-1,1,-1,1,-2.5,2.5],"vols":[-0.5,-0.5,-1.5,-1.5,-4,-4,-5.5,-7,-7,-2,-2,-4.5,-4.5,-3,-3],"cores":[-1,-1,-1,-1,-1,-1,-1,1,1,-1,-1,-1,-1,-1,-1],"vocal_parts":1,"song_scroll_speed":2300,"bank":"sfx/cowbell_bank.milo","anim_tempo":32,"preview":[102632,132632],"rank_drum":268,"rank_guitar":333,"rank_bass":210,"rank_vocals":181,"rank_band":258,"genre":"glam","vocal_gender":"male","format":10,"version":30,"album_art":true,"album_name":"The Final Countdown","album_track_number":1,"year_released":1986,"rating":1,"game_origin":"lego","base_points":642277,"encoding":"latin1","drum_bank":"sfx/rb2_kit01_bank.milo","vocal_tonic_note":6,"song_tonality":1,"extra_authoring":["disc_update"],"rank_keys":269,"rank_real_keys":327,"keys_author":"titiln","upgrade_version":1,"rank_real_guitar":530,"rank_real_bass":275,"real_guitar_tuning":[0,0,0,0,0,0],"real_bass_tuning":[0,0,0,0],"strings_author":"Carl Mylo, RK","song_length":309545,"solo":["guitar","vocal_percussion"]},{"id":"thepassenger","name":"The Passenger","artist":"Iggy Pop","fake":false,"master":true,"context":918,"song_id":786,"songname":"thepassenger","tracks_count":[6,1,2,2,2,0],"pans":[-1,1,-1,1,-1,1,0,-1,1,-1,1,-1,1],"vols":[-3,-3,-2,-2,-3,-3,-1,-3,-3,-1,-1,-4,-4],"cores":[-1,-1,-1,-1,-1,-1,-1,1,1,-1,-1,-1,-1],"vocal_parts":1,"song_scroll_speed":2300,"bank":"sfx/tambourine_bank.milo","anim_tempo":32,"preview":[53894,83894],"rank_drum":201,"rank_guitar":203,"rank_bass":121,"rank_vocals":128,"rank_band":202,"genre":"rock","vocal_gender":"male","format":10,"version":30,"album_art":true,"album_name":"Lust for Life","album_track_number":4,"year_released":1977,"rating":1,"game_origin":"lego","base_points":683290,"encoding":"latin1","drum_bank":"sfx/rb2_kit01_bank.milo","vocal_tonic_note":9,"song_tonality":1,"extra_authoring":["disc_update"],"rank_keys":170,"rank_real_keys":170,"keys_author":"TheSheepQueen","song_length":293636},{"id":"thunder","name":"Thunder","artist":"Boys Like Girls","fake":false,"master":true,"context":930,"song_id":787,"songname":"thunder","tracks_count":[5,1,2,2,2,0],"pans":[0,-1,1,-1,1,0,-1,1,-1,1,-1,1],"vols":[-1,-1.5,-1.5,-3,-3,-2.5,-4.5,-4.5,-3,-3,-4.5,-4.5],"cores":[-1,-1,-1,-1,-1,-1,1,1,-1,-1,-1,-1],"vocal_parts":1,"hopo_threshold":90,"song_scroll_speed":2300,"bank":"sfx/tambourine_bank.milo","anim_tempo":32,"preview":[44588,74588],"rank_drum":119,"rank_guitar":136,"rank_bass":140,"rank_vocals":160,"rank_band":126,"genre":"emo","vocal_gender":"male","format":10,"version":30,"album_art":true,"album_name":"Boys Like Girls","album_track_number":5,"year_released":2006,"rating":1,"game_origin":"lego","base_points":460048,"encoding":"latin1","drum_bank":"sfx/rb2_kit01_bank.milo","vocal_tonic_note":2,"song_tonality":0,"extra_authoring":["disc_update"],"rank_keys":180,"rank_real_keys":218,"keys_author":"SonicSBL","song_length":244090},{"id":"ticktickboom","name":"Tick Tick Boom","artist":"The Hives","fake":false,"master":true,"context":908,"song_id":788,"songname":"ticktickboom","tracks_count":[6,1,2,2,2,0],"pans":[-1,1,-1,1,-1,1,0,-1,1,-1,1,-1,1],"vols":[-1,-1,-1,-1,-3,-3,-1.5,-2,-2,-2.2,-2.2,-3,-3],"cores":[-1,-1,-1,-1,-1,-1,-1,1,1,-1,-1,-1,-1],"vocal_parts":1,"song_scroll_speed":2300,"bank":"sfx/tambourine_bank.milo","anim_tempo":32,"preview":[17212,47212],"rank_drum":276,"rank_guitar":188,"rank_bass":219,"rank_vocals":240,"rank_band":221,"genre":"punk","vocal_gender":"male","format":10,"version":30,"album_art":true,"album_name":"The Black and White Album","album_track_number":1,"year_released":2007,"rating":1,"game_origin":"lego","base_points":509056,"encoding":"latin1","drum_bank":"sfx/rb2_kit01_bank.milo","vocal_tonic_note":11,"song_tonality":1,"extra_authoring":["disc_update"],"rank_keys":153,"rank_real_keys":153,"keys_author":"TheSheepQueen","upgrade_version":1,"rank_real_guitar":262,"rank_real_bass":240,"real_guitar_tuning":[0,0,0,0,0,0],"real_bass_tuning":[0,0,0,0],"strings_author":"RK","song_length":207272},{"id":"twoprinces","name":"Two Princes","artist":"Spin Doctors","fake":false,"master":true,"context":914,"song_id":789,"songname":"twoprinces","tracks_count":[6,1,2,2,0,2],"pans":[-1,1,-1,1,-1,1,0,-1,1,-1,1,-1,1],"vols":[-2,-2,-3,-3,-5,-5,-3,-3,-3,-2.5,-2.5,-4,-4],"cores":[-1,-1,-1,-1,-1,-1,-1,1,1,-1,-1,-1,-1],"vocal_parts":3,"song_scroll_speed":2300,"bank":"sfx/tambourine_bank.milo","anim_tempo":32,"preview":[46816,74829],"rank_drum":361,"rank_guitar":236,"rank_bass":303,"rank_vocals":219,"rank_band":325,"genre":"alternative","vocal_gender":"male","format":10,"version":3,"album_art":true,"album_name":"Pocket Full of Kryptonite","album_track_number":7,"year_released":1991,"rating":1,"tuning_offset_cents":15,"game_origin":"lego","base_points":702204,"encoding":"latin1","drum_bank":"sfx/rb2_kit01_bank.milo","vocal_tonic_note":2,"song_tonality":0,"extra_authoring":["disc_update"],"song_length":270909,"solo":["guitar"],"loading_phrase":"The Spin Doctors appeared on Sesame Street and sang an alternate version of \"Two Princes\" that emphasized the importance of sharing."},{"id":"valerie","name":"Valerie","artist":"The Zutons","fake":false,"master":true,"context":923,"song_id":790,"songname":"valerie","tracks_count":[6,1,2,2,2,0],"pans":[-1,1,-1,1,-1,1,0,-1,1,-1,1,-1,1],"vols":[-2,-2,-2.5,-2.5,-2.5,-2.5,-0.5,-2.5,-2.5,-2.5,-2.5,-2.5,-2.5],"cores":[-1,-1,-1,-1,-1,-1,-1,1,1,-1,-1,-1,-1],"vocal_parts":1,"hopo_threshold":90,"song_scroll_speed":2300,"bank":"sfx/handclap_bank.milo","anim_tempo":16,"preview":[45696,75696],"rank_drum":231,"rank_guitar":212,"rank_bass":184,"rank_vocals":179,"rank_band":205,"genre":"poprock","vocal_gender":"male","format":10,"version":30,"album_art":true,"album_name":"Tired of Hanging Around","album_track_number":3,"year_released":2006,"rating":1,"game_origin":"lego","base_points":456549,"encoding":"latin1","drum_bank":"sfx/rb2_kit01_bank.milo","vocal_tonic_note":3,"song_tonality":0,"extra_authoring":["disc_update"],"rank_keys":195,"rank_real_keys":195,"keys_author":"SonicSBL, BowlsforRick","song_length":243636},{"id":"walkingonsunshine","name":"Walking on Sunshine","artist":"Katrina and the Waves","fake":false,"master":true,"context":922,"song_id":791,"songname":"walkingonsunshine","tracks_count":[6,1,2,2,2,0,2],"pans":[-1,1,-1,1,-1,1,0,-1,1,-1,1,-1,1,-2.5,2.5],"vols":[-0.5,-0.5,-0.5,-0.5,-3.5,-3.5,-3.5,-6,-6,-3,-3,-4,-4,-3.5,-3.5],"cores":[-1,-1,-1,-1,-1,-1,-1,1,1,-1,-1,-1,-1,-1,-1],"vocal_parts":1,"song_scroll_speed":2300,"bank":"sfx/handclap_bank.milo","anim_tempo":32,"preview":[41100,69400],"rank_drum":236,"rank_guitar":211,"rank_bass":229,"rank_vocals":181,"rank_band":213,"genre":"poprock","vocal_gender":"female","format":10,"version":30,"album_art":true,"year_released":1985,"rating":1,"game_origin":"lego","base_points":631567,"encoding":"latin1","drum_bank":"sfx/rb2_kit01_bank.milo","vocal_tonic_note":10,"song_tonality":0,"extra_authoring":["disc_update"],"rank_keys":211,"rank_real_keys":269,"keys_author":"TheSheepQueen","song_length":241363,"solo":["vocal_percussion"],"year_recorded":2004,"loading_phrase":"Katrina & The Waves' \"Walking on Sunshine\" was the first track on Jack Black's Monday Morning Mixtape in the movie \"High Fidelity\", as well as Philip J. Fry's favorite song on \"Futurama\"."},{"id":"wearethechampions","name":"We Are the Champions","artist":"Queen","fake":false,"master":true,"context":917,"song_id":792,"songname":"wearethechampions","tracks_count":[5,1,2,2,0,2,2],"pans":[0,-1,1,-1,1,0,-1,1,-1,1,-1,1,-2.5,2.5],"vols":[-0.5,-1.2,-1.2,-1.2,-1.2,-5.7,-5.2,-5.2,-2.2,-2.2,-2,-2,-3.8,-3.8],"cores":[-1,-1,-1,-1,-1,-1,1,1,-1,-1,-1,-1,-1,-1],"vocal_parts":1,"hopo_threshold":90,"song_scroll_speed":2300,"bank":"sfx/tambourine_bank.milo","anim_tempo":16,"preview":[40000,70000],"rank_drum":123,"rank_guitar":145,"rank_bass":160,"rank_vocals":192,"rank_band":113,"genre":"classicrock","vocal_gender":"male","format":10,"version":3,"album_art":true,"album_name":"News of the World","album_track_number":2,"year_released":1977,"rating":1,"game_origin":"lego","base_points":273344,"encoding":"latin1","song_length":192272,"loading_phrase":"According to Freddie Mercury, the song \"We Are the Champions\" was composed with football chants in mind. He wanted a song that mass audiences would want to participitate in."},{"id":"wewillrockyou1","name":"We Will Rock You","artist":"Queen","fake":false,"master":true,"context":916,"song_id":793,"songname":"wewillrockyou1","tracks_count":[2,2,2,2,0,2,2],"pans":[-1,1,-1,1,-1,1,-1,1,-1,1,-2.5,2.5],"vols":[-1,-1,-1,-1,-1,-1,-2,-2,-2,-2,-2.5,-2.5],"cores":[-1,-1,-1,-1,1,1,-1,-1,-1,-1,-1,-1],"vocal_parts":1,"song_scroll_speed":2300,"bank":"sfx/handclap_bank.milo","anim_tempo":16,"preview":[17450,37450],"rank_drum":93,"rank_guitar":95,"rank_bass":96,"rank_vocals":225,"rank_band":99,"genre":"classicrock","vocal_gender":"male","format":10,"version":3,"album_art":true,"album_name":"News of the World","album_track_number":1,"year_released":1977,"rating":1,"tuning_offset_cents":-50,"game_origin":"lego","base_points":217992,"encoding":"latin1","song_length":130909,"solo":["guitar","vocal_percussion"],"loading_phrase":"'We Will Rock You' has been covered by many artists over the years - including Axl Rose, Warrant, Linda Ronstadt, and Nickelback."},{"id":"wordup","name":"Word Up!","artist":"KoRn","fake":false,"master":true,"context":919,"song_id":794,"songname":"wordup","tracks_count":[5,1,2,2,0,2],"pans":[0,-1,1,-1,1,0,-1,1,-1,1,-1,1],"vols":[-1,-3,-3,-4,-4,-3,-3.5,-3.5,-3,-3,-4.5,-4.5],"cores":[-1,-1,-1,-1,-1,-1,1,1,-1,-1,-1,-1],"vocal_parts":3,"song_scroll_speed":2300,"bank":"sfx/tambourine_bank.milo","anim_tempo":32,"preview":[45400,75400],"rank_drum":221,"rank_guitar":204,"rank_bass":226,"rank_vocals":148,"rank_band":199,"genre":"numetal","vocal_gender":"male","format":10,"version":3,"album_art":true,"album_name":"Greatest Hits, Vol. 1","album_track_number":1,"year_released":2004,"rating":1,"game_origin":"lego","base_points":340049,"encoding":"latin1","drum_bank":"sfx/rb2_kit01_bank.milo","vocal_tonic_note":6,"song_tonality":1,"extra_authoring":["disc_update"],"song_length":171818,"solo":["guitar"],"loading_phrase":"'Word Up' was originally a hit for funk/hip-hop band Cameo, and was their first U.S. Top 40 hit. The song has since been covered many times, most notably by Finnish humppa band Eläkeläiset, but was also a modest hit for Melanie B of The Spice Girls."},{"id":"yougiveloveabadname","name":"You Give Love a Bad Name","artist":"Bon Jovi","fake":false,"master":true,"context":951,"song_id":795,"songname":"yougiveloveabadname","tracks_count":[6,1,2,2,0,2,2],"pans":[-1,1,-1,1,-1,1,0,-1,1,-1,1,-1,1,-2.5,2.5],"vols":[-2.5,-2.5,-3.8,-3.8,-3,-3,-2.5,-1,-1,-2,-2,-3.2,-3.2,-5,-5],"cores":[-1,-1,-1,-1,-1,-1,-1,1,1,-1,-1,-1,-1,-1,-1],"vocal_parts":1,"song_scroll_speed":2300,"bank":"sfx/tambourine_bank.milo","anim_tempo":32,"preview":[60450,90450],"rank_drum":145,"rank_guitar":258,"rank_bass":149,"rank_vocals":176,"rank_band":191,"genre":"rock","vocal_gender":"male","format":10,"version":3,"album_art":true,"album_name":"Slippery When Wet","album_track_number":2,"year_released":1986,"rating":1,"game_origin":"lego","base_points":405773,"encoding":"latin1","song_length":228636,"solo":["guitar"],"loading_phrase":"SHOT THROUGH THE HEART / AND YOU'RE TO BLAME / PS3 HAS NO GAMES"},{"id":"fire","name":"Fire","artist":"The Jimi Hendrix Experience","fake":false,"master":true,"context":906,"song_id":797,"songname":"fire","tracks_count":[2,1,2,2,0,2],"pans":[-1,1,0,-1,1,-1,1,-1,1],"vols":[-0.7,-0.7,-0.7,-2.7,-2.7,-2.7,-2.7,-2.7,-2.7],"cores":[-1,-1,-1,1,1,-1,-1,-1,-1],"vocal_parts":3,"song_scroll_speed":2300,"bank":"sfx/tambourine_bank.milo","anim_tempo":32,"preview":[18483,48483],"rank_drum":371,"rank_guitar":330,"rank_bass":289,"rank_vocals":283,"rank_band":361,"genre":"psychadelic","vocal_gender":"male","format":10,"version":3,"album_art":true,"album_name":"Are You Experienced","album_track_number":8,"year_released":1967,"rating":1,"game_origin":"lego","base_points":426904,"encoding":"latin1","drum_bank":"sfx/rb2_kit01_bank.milo","vocal_tonic_note":2,"song_tonality":1,"extra_authoring":["disc_update"],"upgrade_version":1,"rank_real_guitar":275,"rank_real_bass":215,"real_guitar_tuning":[0,0,0,0,0,0],"real_bass_tuning":[0,0,0,0],"strings_author":"RK","song_length":166363,"solo":["guitar"],"loading_phrase":"The lyrics to the song \"Fire\" were partly inspired by an unco-operative Great Dane that would not let Jimi Hendrix warm himself by the open fire."}]